divination/__init__.py
divination/driver.py
divination/impl.py
divination/lindriver.py
divination/windriver.py
divination-2.0.1.dist-info/LICENSE
divination-2.0.1.dist-info/METADATA
divination-2.0.1.dist-info/WHEEL
divination-2.0.1.dist-info/top_level.txt
divination-2.0.1.dist-info/RECORD
