Metadata-Version: 2.1
Name: divination
Version: 2.0.1
Summary: Python module for hardware and physmem inspection
Home-page: https://github.com/depletionmode/divination
Author: David Kaplan <@depletionmode>
License: UNKNOWN
Platform: UNKNOWN
Classifier: Programming Language :: Python :: 3
Classifier: Operating System :: OS Independent
Classifier: License :: OSI Approved :: MIT License
Classifier: Development Status :: 4 - Beta
